torchbones/__init__.py
torchbones/main.py
torchbones-1.2.6.dist-info/METADATA
torchbones-1.2.6.dist-info/WHEEL
torchbones-1.2.6.dist-info/top_level.txt
torchbones-1.2.6.dist-info/RECORD
