Metadata-Version: 2.1
Name: torchbones
Version: 1.2.6
Summary: A user friendly interface for implementing and training a deep neural network in pytorch
Author: Olive Ross
Author-email: ogr8@cornell.edu
Requires-Dist: pandas
Requires-Dist: torch
Requires-Dist: numpy
Requires-Dist: matplotlib
Requires-Dist: scikit-learn
